{
  "source": {
    "mode": "scraper",
    "homepage": "https://pelotainvernal.com/",
    "scraped_at": "2025-11-13T02:07:57.594Z",
    "tz": "America/Santo_Domingo"
  },
  "tracked_ids": [
    1952,
    1953
  ],
  "live": [
    {
      "id": 1952,
      "status": 2,
      "roundText": "Baja 8va",
      "currentInningNum": 8,
      "atBat": null,
      "lastPlayByPlay": "Leury García Ponche (K) ",
      "counts": {
        "balls": 1,
        "strikes": 1,
        "outs": 2
      },
      "base": {
        "on1B": true,
        "on2B": true,
        "on3B": true,
        "runners": 3,
        "mask": 8
      },
      "battingTeam": "homeTeam",
      "score": {
        "away": {
          "name": "Leones",
          "abbr": "LE",
          "R": 5,
          "H": 4,
          "E": 1
        },
        "home": {
          "name": "Gigantes",
          "abbr": "GC",
          "R": 2,
          "H": 10,
          "E": 2
        }
      },
      "threat": 36,
      "updated_at": "2025-11-13T02:07:57.594Z"
    },
    {
      "id": 1953,
      "status": 2,
      "roundText": "Baja 7ma",
      "currentInningNum": 7,
      "atBat": null,
      "lastPlayByPlay": "Vidal Brujan Out: Elevado al Jardinero Central",
      "counts": {
        "balls": 2,
        "strikes": 0,
        "outs": 1
      },
      "base": {
        "on1B": true,
        "on2B": false,
        "on3B": false,
        "runners": 1,
        "mask": 2
      },
      "battingTeam": "homeTeam",
      "score": {
        "away": {
          "name": "Aguilas",
          "abbr": "AC",
          "R": 4,
          "H": 8,
          "E": 1
        },
        "home": {
          "name": "Estrellas",
          "abbr": "EO",
          "R": 3,
          "H": 4,
          "E": 1
        }
      },
      "threat": 22,
      "updated_at": "2025-11-13T02:07:57.594Z"
    }
  ]
}
