{
  "source": {
    "mode": "scraper",
    "homepage": "https://pelotainvernal.com/",
    "scraped_at": "2025-11-10T00:10:22.635Z",
    "tz": "America/Santo_Domingo"
  },
  "tracked_ids": [
    2091,
    1946
  ],
  "live": [
    {
      "id": 2091,
      "status": 2,
      "roundText": "Baja 7ma",
      "currentInningNum": 7,
      "atBat": null,
      "lastPlayByPlay": "Leody Taveras Elevado de Sacrificio Carrera Empujada",
      "counts": {
        "balls": 0,
        "strikes": 0,
        "outs": 2
      },
      "base": {
        "on1B": false,
        "on2B": false,
        "on3B": false,
        "runners": 0,
        "mask": 1
      },
      "battingTeam": "homeTeam",
      "score": {
        "away": {
          "name": "Gigantes",
          "abbr": "GC",
          "R": 3,
          "H": 5,
          "E": 0
        },
        "home": {
          "name": "Aguilas",
          "abbr": "AC",
          "R": 3,
          "H": 2,
          "E": 1
        }
      },
      "threat": 4,
      "updated_at": "2025-11-10T00:10:22.635Z"
    },
    {
      "id": 1946,
      "status": 2,
      "roundText": "Alta 8va",
      "currentInningNum": 8,
      "atBat": null,
      "lastPlayByPlay": "Raimel Tapia Ponche (K) ",
      "counts": {
        "balls": 0,
        "strikes": 0,
        "outs": 2
      },
      "base": {
        "on1B": false,
        "on2B": false,
        "on3B": false,
        "runners": 0,
        "mask": 1
      },
      "battingTeam": "awayTeam",
      "score": {
        "away": {
          "name": "Estrellas",
          "abbr": "EO",
          "R": 4,
          "H": 6,
          "E": 1
        },
        "home": {
          "name": "Toros",
          "abbr": "TE",
          "R": 6,
          "H": 9,
          "E": 1
        }
      },
      "threat": 4,
      "updated_at": "2025-11-10T00:10:22.635Z"
    }
  ]
}
